ragmatic/__init__.py
ragmatic/common_types.py
ragmatic/actions/__init__.py
ragmatic/actions/_types.py
ragmatic/actions/action_factory.py
ragmatic/actions/bases.py
ragmatic/actions/encode.py
ragmatic/actions/rag.py
ragmatic/actions/summarize.py
ragmatic/cli/__init__.py
ragmatic/cli/cli.py
ragmatic/cli/commands/__init__.py
ragmatic/cli/commands/rag.py
ragmatic/cli/commands/run.py
ragmatic/cli/configuration/__init__.py
ragmatic/cli/configuration/_types.py
ragmatic/cli/configuration/tools.py
ragmatic/cli/configuration/presets/__init__.py
ragmatic/cli/configuration/presets/_types.py
ragmatic/cli/configuration/presets/local_docs_preset.py
ragmatic/cli/configuration/presets/preset_factory.py
ragmatic/cli/configuration/presets/pycode_preset.py
ragmatic/document_sources/__init__.py
ragmatic/document_sources/bases.py
ragmatic/document_sources/filesystem.py
ragmatic/document_sources/source_factory.py
ragmatic/document_sources/storage.py
ragmatic/embeddings/__init__.py
ragmatic/embeddings/bases.py
ragmatic/embeddings/embedder_factory.py
ragmatic/embeddings/hf_sentence_transformers.py
ragmatic/embeddings/hf_transformers.py
ragmatic/llm_ops/__init__.py
ragmatic/llm_ops/anthropic_.py
ragmatic/llm_ops/bases.py
ragmatic/llm_ops/client_factory.py
ragmatic/llm_ops/openai_.py
ragmatic/rag/__init__.py
ragmatic/rag/bases.py
ragmatic/rag/generic.py
ragmatic/rag/pycode_rag_agent.py
ragmatic/rag/rag_agent_factory.py
ragmatic/storage/__init__.py
ragmatic/storage/bases.py
ragmatic/storage/store_factory.py
ragmatic/storage/pydict/__init__.py
ragmatic/storage/pydict/obj_store.py
ragmatic/storage/pydict/omni_store.py
ragmatic/storage/pydict/text_doc_store.py
ragmatic/storage/pydict/vector_store.py
ragmatic/summarization/__init__.py
ragmatic/summarization/bases.py
ragmatic/summarization/py_code_summarizer.py
ragmatic/summarization/summarizer_factory.py
ragmatic/utils/__init__.py
ragmatic/utils/collection_key_formatter.py
ragmatic/utils/factory.py
ragmatic/utils/refs.py
ragmatic-0.2.0b1.dist-info/LICENSE
ragmatic-0.2.0b1.dist-info/METADATA
ragmatic-0.2.0b1.dist-info/WHEEL
ragmatic-0.2.0b1.dist-info/entry_points.txt
ragmatic-0.2.0b1.dist-info/top_level.txt
ragmatic-0.2.0b1.dist-info/RECORD
