Metadata-Version: 2.1
Name: ragmatic
Version: 0.2.0b1
Summary: A package for creating retrieval-augmented generation apps
Author-email: John Raines <johndanielraiens@gmail.com>
License: Copyright (c) 2024 John Raines
Project-URL: Homepage, https://github.com/jdraines/ragmatic
Project-URL: Repository, https://github.com/jdraines/ragmatic
Project-URL: Bug Tracker, https://github.com/jdraines/ragmatic/issues
Classifier: Programming Language :: Python :: 3
Classifier: License :: OSI Approved :: MIT License
Classifier: Development Status :: 4 - Beta
Classifier: Programming Language :: Python :: 3
Classifier: Programming Language :: Python :: 3.10
Classifier: Programming Language :: Python :: 3.11
Classifier: Programming Language :: Python :: 3.12
Requires-Python: >=3.10
License-File: LICENSE
Requires-Dist: openai>=1.37.1
Requires-Dist: tenacity>=9.0.0
Requires-Dist: networkx>=3.3
Requires-Dist: pydantic>=2.8.2
Requires-Dist: joblib>=1.4.2
Requires-Dist: click>=8.1.7
Requires-Dist: pyyaml>=6.0.1
Requires-Dist: numpy>=2.0.1
Requires-Dist: deepmerge>=1.1.1
Provides-Extra: anthropic
Requires-Dist: anthropic>=0.34.1; extra == "anthropic"
Provides-Extra: dev
Requires-Dist: pytest; extra == "dev"
Requires-Dist: pytest-cov; extra == "dev"
Provides-Extra: openai
Requires-Dist: openai>=1.37.1; extra == "openai"
Provides-Extra: sentence-transformers
Requires-Dist: sentence-transformers>=3.0.1; extra == "sentence-transformers"
Provides-Extra: transformers
Requires-Dist: transformers>=4.44; extra == "transformers"
Requires-Dist: torch>=2.4.0; extra == "transformers"
Requires-Dist: scikit-learn>=1.5.1; extra == "transformers"
